
[

  {
    "var":      "elekata",
    "title":    "エレ片のケツビ",
    "dow":      "月",
    "url":      "https://podcasts.apple.com/jp/podcast/%E3%82%A8%E3%83%AC%E7%89%87%E3%81%AE%E3%82%B1%E3%83%84%E3%83%93/id1560299989",
    "platform": "apple_podcast",
    "scraper":  "selenium"
  },

  {
    "var":      "rocket",
    "title":    "ロケットマンショー",
    "dow":      "火",
    "url":      "https://podcasts.apple.com/jp/podcast/%E3%83%AD%E3%82%B1%E3%83%83%E3%83%88%E3%83%9E%E3%83%B3%E3%82%B7%E3%83%A7%E3%83%BC/id1738995329",
    "platform": "apple_podcast",
    "scraper":  "selenium"
  },

  {
    "var":      "elekata",
    "dow":      "",
    "title":    "エレ片のケツビ",
    "url":      "https://feeds.megaphone.fm/TBS2752996527",
    "anchor":   "新録",
    "platform": "megaphone_fm",
    "scraper":  "xml"
  },

  {
    "var":      "elekata",
    "dow":      "",
    "title":    "エレ片のケツビ",
    "url":      "https://radiko.jp/v3/program/station/weekly/TBS.xml",
    "platform": "radiko",
    "scraper":  "xml"
  }

]
